models/__init__.py
models/intranet_partner.py
intranet_partner-0.0.1.dist-info/LICENSE
intranet_partner-0.0.1.dist-info/METADATA
intranet_partner-0.0.1.dist-info/WHEEL
intranet_partner-0.0.1.dist-info/top_level.txt
intranet_partner-0.0.1.dist-info/RECORD
